{
  "blockPositionsSerialized": [
    274810798079,
    274743689216,
    274743689217,
    67108863,
    0,
    1,
    549688705023,
    549621596160,
    549621596161,
    274945015807,
    274877906944,
    274877906945,
    824566611967,
    824499503104,
    824499503105,
    549822922751,
    549755813888,
    549755813889
  ],
  "blockNameIndexes": [
    0,
    0,
    0,
    1,
    1,
    1,
    0,
    2,
    0,
    1,
    1,
    1,
    0,
    0,
    0,
    1,
    1,
    1
  ],
  "blockIndexToNameMap": {
    "0": "minecraft:grass",
    "1": "minecraft:stone",
    "2": "minecraft:lava"
  }
}