{
  "result": {
    "item": "divinefavor:talisman_summon_stray"
  },
  "stones": [
    "divinefavor:calling_stone_loon"
  ],
  "ingredients": [
    {
      "type": "ore",
      "ore": "paper"
    },
    {
      "type": "ore",
      "ore": "dyeWhite"
    },
    {
      "type": "ore",
      "ore": "bone"
    },
    {
      "type": "stack",
      "item": "minecraft:arrow"
    },
    {
      "type": "stack",
      "item": "minecraft:milk_bucket"
    },
    {
      "type": "stack",
      "item": "minecraft:fermented_spider_eye"
    }
  ]
}